{"metadata": {"dbt_schema_version": "https://schemas.getdbt.com/dbt/catalog/v1.json", "dbt_version": "1.11.8", "generated_at": "2026-04-08T19:28:15.223647Z", "invocation_id": "10e13a1c-b543-4a42-961e-ea1af29c71c6", "invocation_started_at": "2026-04-08T19:27:53.657965Z", "env": {}}, "nodes": {"model.mortgage_analytics.int_delinquency_rollforward": {"metadata": {"type": "BASE TABLE", "schema": "analytics_int_mortgage", "name": "int_delinquency_rollforward", "database": "neondb", "comment": "Month-over-month delinquency bucket transitions and UPB totals.", "owner": "neondb_owner"}, "columns": {"reporting_month": {"type": "date", "index": 1, "name": "reporting_month", "comment": null}, "from_delinquency_bucket": {"type": "text", "index": 2, "name": "from_delinquency_bucket", "comment": null}, "to_delinquency_bucket": {"type": "text", "index": 3, "name": "to_delinquency_bucket", "comment": null}, "loan_count": {"type": "bigint", "index": 4, "name": "loan_count", "comment": null}, "total_current_actual_upb": {"type": "numeric", "index": 5, "name": "total_current_actual_upb", "comment": null}}, "stats": {"has_stats": {"id": "has_stats", "label": "Has Stats?", "value": false, "include": false, "description": "Indicates whether there are statistics for this table"}}, "unique_id": "model.mortgage_analytics.int_delinquency_rollforward"}, "model.mortgage_analytics.int_latest_loan_status": {"metadata": {"type": "BASE TABLE", "schema": "analytics_int_mortgage", "name": "int_latest_loan_status", "database": "neondb", "comment": "Latest available monthly snapshot per loan.", "owner": "neondb_owner"}, "columns": {"loan_id": {"type": "text", "index": 1, "name": "loan_id", "comment": null}, "latest_reporting_month": {"type": "date", "index": 2, "name": "latest_reporting_month", "comment": null}, "current_actual_upb": {"type": "numeric", "index": 3, "name": "current_actual_upb", "comment": null}, "delinquency_status_code": {"type": "text", "index": 4, "name": "delinquency_status_code", "comment": null}, "delinquency_bucket": {"type": "text", "index": 5, "name": "delinquency_bucket", "comment": null}, "loan_age_months": {"type": "integer", "index": 6, "name": "loan_age_months", "comment": null}, "remaining_months_to_legal_maturity": {"type": "integer", "index": 7, "name": "remaining_months_to_legal_maturity", "comment": null}, "repurchase_flag": {"type": "text", "index": 8, "name": "repurchase_flag", "comment": null}, "modification_flag": {"type": "text", "index": 9, "name": "modification_flag", "comment": null}, "zero_balance_code": {"type": "text", "index": 10, "name": "zero_balance_code", "comment": null}, "zero_balance_effective_date": {"type": "date", "index": 11, "name": "zero_balance_effective_date", "comment": null}, "current_interest_rate": {"type": "numeric", "index": 12, "name": "current_interest_rate", "comment": null}, "current_deferred_upb": {"type": "numeric", "index": 13, "name": "current_deferred_upb", "comment": null}, "due_date_last_paid_installment": {"type": "date", "index": 14, "name": "due_date_last_paid_installment", "comment": null}, "estimated_loan_to_value": {"type": "numeric", "index": 15, "name": "estimated_loan_to_value", "comment": null}, "zero_balance_removal_upb": {"type": "numeric", "index": 16, "name": "zero_balance_removal_upb", "comment": null}, "delinquent_accrued_interest": {"type": "numeric", "index": 17, "name": "delinquent_accrued_interest", "comment": null}, "delinquency_due_to_disaster": {"type": "text", "index": 18, "name": "delinquency_due_to_disaster", "comment": null}, "borrower_assistance_plan": {"type": "text", "index": 19, "name": "borrower_assistance_plan", "comment": null}, "current_month_modification_cost": {"type": "numeric", "index": 20, "name": "current_month_modification_cost", "comment": null}, "interest_bearing_upb": {"type": "numeric", "index": 21, "name": "interest_bearing_upb", "comment": null}, "first_payment_date": {"type": "date", "index": 22, "name": "first_payment_date", "comment": null}, "maturity_date": {"type": "date", "index": 23, "name": "maturity_date", "comment": null}, "credit_score": {"type": "integer", "index": 24, "name": "credit_score", "comment": null}, "original_upb": {"type": "bigint", "index": 25, "name": "original_upb", "comment": null}, "original_interest_rate": {"type": "numeric", "index": 26, "name": "original_interest_rate", "comment": null}, "original_ltv": {"type": "numeric", "index": 27, "name": "original_ltv", "comment": null}, "original_cltv": {"type": "numeric", "index": 28, "name": "original_cltv", "comment": null}, "original_dti": {"type": "numeric", "index": 29, "name": "original_dti", "comment": null}, "original_loan_term_months": {"type": "integer", "index": 30, "name": "original_loan_term_months", "comment": null}, "loan_purpose": {"type": "text", "index": 31, "name": "loan_purpose", "comment": null}, "property_state": {"type": "text", "index": 32, "name": "property_state", "comment": null}, "property_type": {"type": "text", "index": 33, "name": "property_type", "comment": null}, "occupancy_status": {"type": "text", "index": 34, "name": "occupancy_status", "comment": null}, "channel": {"type": "text", "index": 35, "name": "channel", "comment": null}, "seller_name": {"type": "text", "index": 36, "name": "seller_name", "comment": null}, "servicer_name": {"type": "text", "index": 37, "name": "servicer_name", "comment": null}, "source_year": {"type": "smallint", "index": 38, "name": "source_year", "comment": null}, "source_quarter": {"type": "smallint", "index": 39, "name": "source_quarter", "comment": null}}, "stats": {"has_stats": {"id": "has_stats", "label": "Has Stats?", "value": false, "include": false, "description": "Indicates whether there are statistics for this table"}}, "unique_id": "model.mortgage_analytics.int_latest_loan_status"}, "model.mortgage_analytics.int_loan_monthly_snapshot": {"metadata": {"type": "BASE TABLE", "schema": "analytics_int_mortgage", "name": "int_loan_monthly_snapshot", "database": "neondb", "comment": "Loan-month grain view joining staged monthly performance to origination attributes. Materialized incrementally (merge on loan_id, reporting_month) so each run processes only new loan-months and shorter statements are less likely to hit Neon connection limits. For lag columns, the prior in-database month is unioned into the window for each touched loan. Optional dbt vars for bounded loads: snapshot_reporting_month_start / snapshot_reporting_month_end (YYYY-MM-DD, compared to reporting_month). Use overlapping backfill windows only with care.\n", "owner": "neondb_owner"}, "columns": {"loan_id": {"type": "text", "index": 1, "name": "loan_id", "comment": null}, "reporting_month": {"type": "date", "index": 2, "name": "reporting_month", "comment": null}, "current_actual_upb": {"type": "numeric", "index": 3, "name": "current_actual_upb", "comment": null}, "delinquency_status_code": {"type": "text", "index": 4, "name": "delinquency_status_code", "comment": null}, "loan_age_months": {"type": "integer", "index": 5, "name": "loan_age_months", "comment": null}, "remaining_months_to_legal_maturity": {"type": "integer", "index": 6, "name": "remaining_months_to_legal_maturity", "comment": null}, "repurchase_flag": {"type": "text", "index": 7, "name": "repurchase_flag", "comment": null}, "modification_flag": {"type": "text", "index": 8, "name": "modification_flag", "comment": null}, "zero_balance_code": {"type": "text", "index": 9, "name": "zero_balance_code", "comment": "Non-null when loan is removed from active portfolio."}, "zero_balance_effective_date": {"type": "date", "index": 10, "name": "zero_balance_effective_date", "comment": null}, "current_interest_rate": {"type": "numeric", "index": 11, "name": "current_interest_rate", "comment": null}, "current_deferred_upb": {"type": "numeric", "index": 12, "name": "current_deferred_upb", "comment": null}, "due_date_last_paid_installment": {"type": "date", "index": 13, "name": "due_date_last_paid_installment", "comment": null}, "estimated_loan_to_value": {"type": "numeric", "index": 14, "name": "estimated_loan_to_value", "comment": null}, "zero_balance_removal_upb": {"type": "numeric", "index": 15, "name": "zero_balance_removal_upb", "comment": null}, "delinquent_accrued_interest": {"type": "numeric", "index": 16, "name": "delinquent_accrued_interest", "comment": null}, "delinquency_due_to_disaster": {"type": "text", "index": 17, "name": "delinquency_due_to_disaster", "comment": null}, "borrower_assistance_plan": {"type": "text", "index": 18, "name": "borrower_assistance_plan", "comment": null}, "current_month_modification_cost": {"type": "numeric", "index": 19, "name": "current_month_modification_cost", "comment": null}, "interest_bearing_upb": {"type": "numeric", "index": 20, "name": "interest_bearing_upb", "comment": null}, "first_payment_date": {"type": "date", "index": 21, "name": "first_payment_date", "comment": null}, "maturity_date": {"type": "date", "index": 22, "name": "maturity_date", "comment": null}, "credit_score": {"type": "integer", "index": 23, "name": "credit_score", "comment": null}, "original_upb": {"type": "bigint", "index": 24, "name": "original_upb", "comment": null}, "original_interest_rate": {"type": "numeric", "index": 25, "name": "original_interest_rate", "comment": null}, "original_ltv": {"type": "numeric", "index": 26, "name": "original_ltv", "comment": null}, "original_cltv": {"type": "numeric", "index": 27, "name": "original_cltv", "comment": null}, "original_dti": {"type": "numeric", "index": 28, "name": "original_dti", "comment": null}, "original_loan_term_months": {"type": "integer", "index": 29, "name": "original_loan_term_months", "comment": null}, "loan_purpose": {"type": "text", "index": 30, "name": "loan_purpose", "comment": null}, "property_state": {"type": "text", "index": 31, "name": "property_state", "comment": null}, "property_type": {"type": "text", "index": 32, "name": "property_type", "comment": null}, "occupancy_status": {"type": "text", "index": 33, "name": "occupancy_status", "comment": null}, "channel": {"type": "text", "index": 34, "name": "channel", "comment": null}, "seller_name": {"type": "text", "index": 35, "name": "seller_name", "comment": null}, "servicer_name": {"type": "text", "index": 36, "name": "servicer_name", "comment": null}, "source_year": {"type": "smallint", "index": 37, "name": "source_year", "comment": null}, "source_quarter": {"type": "smallint", "index": 38, "name": "source_quarter", "comment": null}, "delinquency_bucket": {"type": "text", "index": 39, "name": "delinquency_bucket", "comment": null}, "prior_current_actual_upb": {"type": "numeric", "index": 40, "name": "prior_current_actual_upb", "comment": null}, "prior_delinquency_status_code": {"type": "text", "index": 41, "name": "prior_delinquency_status_code", "comment": null}, "prior_delinquency_bucket": {"type": "text", "index": 42, "name": "prior_delinquency_bucket", "comment": null}}, "stats": {"has_stats": {"id": "has_stats", "label": "Has Stats?", "value": false, "include": false, "description": "Indicates whether there are statistics for this table"}}, "unique_id": "model.mortgage_analytics.int_loan_monthly_snapshot"}, "model.mortgage_analytics.dim_calendar": {"metadata": {"type": "BASE TABLE", "schema": "analytics_mart_mortgage", "name": "dim_calendar", "database": "neondb", "comment": null, "owner": "neondb_owner"}, "columns": {"calendar_month": {"type": "date", "index": 1, "name": "calendar_month", "comment": null}, "calendar_year": {"type": "integer", "index": 2, "name": "calendar_year", "comment": null}, "calendar_quarter": {"type": "integer", "index": 3, "name": "calendar_quarter", "comment": null}, "calendar_month_num": {"type": "integer", "index": 4, "name": "calendar_month_num", "comment": null}, "year_month": {"type": "text", "index": 5, "name": "year_month", "comment": null}}, "stats": {"has_stats": {"id": "has_stats", "label": "Has Stats?", "value": false, "include": false, "description": "Indicates whether there are statistics for this table"}}, "unique_id": "model.mortgage_analytics.dim_calendar"}, "model.mortgage_analytics.dim_delinquency_bucket": {"metadata": {"type": "BASE TABLE", "schema": "analytics_mart_mortgage", "name": "dim_delinquency_bucket", "database": "neondb", "comment": "Canonical delinquency bucket dimension for portfolio analytics.", "owner": "neondb_owner"}, "columns": {"delinquency_bucket": {"type": "text", "index": 1, "name": "delinquency_bucket", "comment": null}, "delinquency_bucket_order": {"type": "integer", "index": 2, "name": "delinquency_bucket_order", "comment": null}, "delinquency_bucket_description": {"type": "text", "index": 3, "name": "delinquency_bucket_description", "comment": null}}, "stats": {"has_stats": {"id": "has_stats", "label": "Has Stats?", "value": false, "include": false, "description": "Indicates whether there are statistics for this table"}}, "unique_id": "model.mortgage_analytics.dim_delinquency_bucket"}, "model.mortgage_analytics.dim_kpi_metric": {"metadata": {"type": "BASE TABLE", "schema": "analytics_mart_mortgage", "name": "dim_kpi_metric", "database": "neondb", "comment": null, "owner": "neondb_owner"}, "columns": {"metric_name": {"type": "text", "index": 1, "name": "metric_name", "comment": null}, "metric_unit_type": {"type": "text", "index": 2, "name": "metric_unit_type", "comment": null}, "metric_description": {"type": "text", "index": 3, "name": "metric_description", "comment": null}, "metric_order": {"type": "integer", "index": 4, "name": "metric_order", "comment": null}}, "stats": {"has_stats": {"id": "has_stats", "label": "Has Stats?", "value": false, "include": false, "description": "Indicates whether there are statistics for this table"}}, "unique_id": "model.mortgage_analytics.dim_kpi_metric"}, "model.mortgage_analytics.dim_loan": {"metadata": {"type": "BASE TABLE", "schema": "analytics_mart_mortgage", "name": "dim_loan", "database": "neondb", "comment": null, "owner": "neondb_owner"}, "columns": {"loan_id": {"type": "text", "index": 1, "name": "loan_id", "comment": null}, "first_payment_date": {"type": "date", "index": 2, "name": "first_payment_date", "comment": null}, "maturity_date": {"type": "date", "index": 3, "name": "maturity_date", "comment": null}, "credit_score": {"type": "integer", "index": 4, "name": "credit_score", "comment": null}, "original_upb": {"type": "bigint", "index": 5, "name": "original_upb", "comment": null}, "original_interest_rate": {"type": "numeric", "index": 6, "name": "original_interest_rate", "comment": null}, "original_ltv": {"type": "numeric", "index": 7, "name": "original_ltv", "comment": null}, "original_cltv": {"type": "numeric", "index": 8, "name": "original_cltv", "comment": null}, "original_dti": {"type": "numeric", "index": 9, "name": "original_dti", "comment": null}, "original_loan_term_months": {"type": "integer", "index": 10, "name": "original_loan_term_months", "comment": null}, "loan_purpose": {"type": "text", "index": 11, "name": "loan_purpose", "comment": null}, "property_state": {"type": "text", "index": 12, "name": "property_state", "comment": null}, "property_type": {"type": "text", "index": 13, "name": "property_type", "comment": null}, "occupancy_status": {"type": "text", "index": 14, "name": "occupancy_status", "comment": null}, "channel": {"type": "text", "index": 15, "name": "channel", "comment": null}, "seller_name": {"type": "text", "index": 16, "name": "seller_name", "comment": null}, "servicer_name": {"type": "text", "index": 17, "name": "servicer_name", "comment": null}, "super_conforming_flag": {"type": "text", "index": 18, "name": "super_conforming_flag", "comment": null}, "preharp_loan_identifier": {"type": "text", "index": 19, "name": "preharp_loan_identifier", "comment": null}, "harp_loan_indicator": {"type": "text", "index": 20, "name": "harp_loan_indicator", "comment": null}, "program_indicator": {"type": "text", "index": 21, "name": "program_indicator", "comment": null}, "property_valuation_method": {"type": "text", "index": 22, "name": "property_valuation_method", "comment": null}, "interest_only_indicator": {"type": "text", "index": 23, "name": "interest_only_indicator", "comment": null}, "mortgage_insurance_cancellation_indicator": {"type": "text", "index": 24, "name": "mortgage_insurance_cancellation_indicator", "comment": null}, "origination_year": {"type": "smallint", "index": 25, "name": "origination_year", "comment": null}, "origination_quarter": {"type": "smallint", "index": 26, "name": "origination_quarter", "comment": null}, "ingested_at": {"type": "timestamp with time zone", "index": 27, "name": "ingested_at", "comment": null}}, "stats": {"has_stats": {"id": "has_stats", "label": "Has Stats?", "value": false, "include": false, "description": "Indicates whether there are statistics for this table"}}, "unique_id": "model.mortgage_analytics.dim_loan"}, "model.mortgage_analytics.fct_delinquency_rollforward": {"metadata": {"type": "BASE TABLE", "schema": "analytics_mart_mortgage", "name": "fct_delinquency_rollforward", "database": "neondb", "comment": "Month-over-month delinquency transitions at from/to bucket grain.", "owner": "neondb_owner"}, "columns": {"reporting_month": {"type": "date", "index": 1, "name": "reporting_month", "comment": null}, "from_delinquency_bucket": {"type": "text", "index": 2, "name": "from_delinquency_bucket", "comment": null}, "to_delinquency_bucket": {"type": "text", "index": 3, "name": "to_delinquency_bucket", "comment": null}, "loan_count": {"type": "bigint", "index": 4, "name": "loan_count", "comment": null}, "total_current_actual_upb": {"type": "numeric", "index": 5, "name": "total_current_actual_upb", "comment": null}}, "stats": {"has_stats": {"id": "has_stats", "label": "Has Stats?", "value": false, "include": false, "description": "Indicates whether there are statistics for this table"}}, "unique_id": "model.mortgage_analytics.fct_delinquency_rollforward"}, "model.mortgage_analytics.fct_loan_monthly_snapshot": {"metadata": {"type": "VIEW", "schema": "analytics_mart_mortgage", "name": "fct_loan_monthly_snapshot", "database": "neondb", "comment": "Loan-month grain fact for dashboard drilldowns and metric calculations. Column tests are disabled: this view scans int_loan_monthly_snapshot (~100M rows); the same constraints are enforced on int_loan_monthly_snapshot and Neon long-running test queries time out.\n", "owner": "neondb_owner"}, "columns": {"loan_id": {"type": "text", "index": 1, "name": "loan_id", "comment": null}, "reporting_month": {"type": "date", "index": 2, "name": "reporting_month", "comment": null}, "current_actual_upb": {"type": "numeric", "index": 3, "name": "current_actual_upb", "comment": null}, "delinquency_status_code": {"type": "text", "index": 4, "name": "delinquency_status_code", "comment": null}, "delinquency_bucket": {"type": "text", "index": 5, "name": "delinquency_bucket", "comment": null}, "loan_age_months": {"type": "integer", "index": 6, "name": "loan_age_months", "comment": null}, "remaining_months_to_legal_maturity": {"type": "integer", "index": 7, "name": "remaining_months_to_legal_maturity", "comment": null}, "repurchase_flag": {"type": "text", "index": 8, "name": "repurchase_flag", "comment": null}, "modification_flag": {"type": "text", "index": 9, "name": "modification_flag", "comment": null}, "zero_balance_code": {"type": "text", "index": 10, "name": "zero_balance_code", "comment": null}, "zero_balance_effective_date": {"type": "date", "index": 11, "name": "zero_balance_effective_date", "comment": null}, "current_interest_rate": {"type": "numeric", "index": 12, "name": "current_interest_rate", "comment": null}, "current_deferred_upb": {"type": "numeric", "index": 13, "name": "current_deferred_upb", "comment": null}, "due_date_last_paid_installment": {"type": "date", "index": 14, "name": "due_date_last_paid_installment", "comment": null}, "estimated_loan_to_value": {"type": "numeric", "index": 15, "name": "estimated_loan_to_value", "comment": null}, "zero_balance_removal_upb": {"type": "numeric", "index": 16, "name": "zero_balance_removal_upb", "comment": null}, "delinquent_accrued_interest": {"type": "numeric", "index": 17, "name": "delinquent_accrued_interest", "comment": null}, "delinquency_due_to_disaster": {"type": "text", "index": 18, "name": "delinquency_due_to_disaster", "comment": null}, "borrower_assistance_plan": {"type": "text", "index": 19, "name": "borrower_assistance_plan", "comment": null}, "current_month_modification_cost": {"type": "numeric", "index": 20, "name": "current_month_modification_cost", "comment": null}, "interest_bearing_upb": {"type": "numeric", "index": 21, "name": "interest_bearing_upb", "comment": null}, "prior_current_actual_upb": {"type": "numeric", "index": 22, "name": "prior_current_actual_upb", "comment": null}, "prior_delinquency_status_code": {"type": "text", "index": 23, "name": "prior_delinquency_status_code", "comment": null}, "prior_delinquency_bucket": {"type": "text", "index": 24, "name": "prior_delinquency_bucket", "comment": null}, "first_payment_date": {"type": "date", "index": 25, "name": "first_payment_date", "comment": null}, "maturity_date": {"type": "date", "index": 26, "name": "maturity_date", "comment": null}, "credit_score": {"type": "integer", "index": 27, "name": "credit_score", "comment": null}, "original_upb": {"type": "bigint", "index": 28, "name": "original_upb", "comment": null}, "original_interest_rate": {"type": "numeric", "index": 29, "name": "original_interest_rate", "comment": null}, "original_ltv": {"type": "numeric", "index": 30, "name": "original_ltv", "comment": null}, "original_cltv": {"type": "numeric", "index": 31, "name": "original_cltv", "comment": null}, "original_dti": {"type": "numeric", "index": 32, "name": "original_dti", "comment": null}, "original_loan_term_months": {"type": "integer", "index": 33, "name": "original_loan_term_months", "comment": null}, "loan_purpose": {"type": "text", "index": 34, "name": "loan_purpose", "comment": null}, "property_state": {"type": "text", "index": 35, "name": "property_state", "comment": null}, "property_type": {"type": "text", "index": 36, "name": "property_type", "comment": null}, "occupancy_status": {"type": "text", "index": 37, "name": "occupancy_status", "comment": null}, "channel": {"type": "text", "index": 38, "name": "channel", "comment": null}, "seller_name": {"type": "text", "index": 39, "name": "seller_name", "comment": null}, "servicer_name": {"type": "text", "index": 40, "name": "servicer_name", "comment": null}, "source_year": {"type": "smallint", "index": 41, "name": "source_year", "comment": null}, "source_quarter": {"type": "smallint", "index": 42, "name": "source_quarter", "comment": null}, "is_active": {"type": "boolean", "index": 43, "name": "is_active", "comment": null}}, "stats": {"has_stats": {"id": "has_stats", "label": "Has Stats?", "value": false, "include": false, "description": "Indicates whether there are statistics for this table"}}, "unique_id": "model.mortgage_analytics.fct_loan_monthly_snapshot"}, "model.mortgage_analytics.fct_portfolio_metric_significance_monthly": {"metadata": {"type": "VIEW", "schema": "analytics_mart_mortgage", "name": "fct_portfolio_metric_significance_monthly", "database": "neondb", "comment": "Long-format KPI fact: classic z-score, robust z (median/MAD), percentile rank in trailing 12 months, skew/kurtosis-based distribution_profile, recommended_method routing, and unified primary_anomaly_score.\n", "owner": "neondb_owner"}, "columns": {"reporting_month": {"type": "date", "index": 1, "name": "reporting_month", "comment": null}, "metric_name": {"type": "text", "index": 2, "name": "metric_name", "comment": null}, "metric_value": {"type": "numeric", "index": 3, "name": "metric_value", "comment": null}, "rn": {"type": "bigint", "index": 4, "name": "rn", "comment": null}, "prior_month_metric_value": {"type": "numeric", "index": 5, "name": "prior_month_metric_value", "comment": null}, "prior_year_metric_value": {"type": "numeric", "index": 6, "name": "prior_year_metric_value", "comment": null}, "trailing_12m_avg": {"type": "numeric", "index": 7, "name": "trailing_12m_avg", "comment": null}, "trailing_12m_stddev": {"type": "numeric", "index": 8, "name": "trailing_12m_stddev", "comment": null}, "rolling_median_12m": {"type": "double precision", "index": 9, "name": "rolling_median_12m", "comment": null}, "rolling_mad_12m": {"type": "double precision", "index": 10, "name": "rolling_mad_12m", "comment": null}, "trailing_12m_skewness": {"type": "numeric", "index": 11, "name": "trailing_12m_skewness", "comment": null}, "trailing_12m_excess_kurtosis": {"type": "numeric", "index": 12, "name": "trailing_12m_excess_kurtosis", "comment": null}, "percentile_rank_12m": {"type": "numeric", "index": 13, "name": "percentile_rank_12m", "comment": null}, "mom_delta": {"type": "numeric", "index": 14, "name": "mom_delta", "comment": null}, "mom_pct_change": {"type": "numeric", "index": 15, "name": "mom_pct_change", "comment": null}, "yoy_delta": {"type": "numeric", "index": 16, "name": "yoy_delta", "comment": null}, "yoy_pct_change": {"type": "numeric", "index": 17, "name": "yoy_pct_change", "comment": null}, "zscore_12m": {"type": "numeric", "index": 18, "name": "zscore_12m", "comment": null}, "is_2sd_outlier": {"type": "boolean", "index": 19, "name": "is_2sd_outlier", "comment": null}, "robust_zscore_12m": {"type": "double precision", "index": 20, "name": "robust_zscore_12m", "comment": null}, "is_2sd_outlier_robust": {"type": "boolean", "index": 21, "name": "is_2sd_outlier_robust", "comment": null}, "distribution_profile": {"type": "text", "index": 22, "name": "distribution_profile", "comment": null}, "recommended_method": {"type": "text", "index": 23, "name": "recommended_method", "comment": null}, "primary_anomaly_score": {"type": "double precision", "index": 24, "name": "primary_anomaly_score", "comment": null}, "is_primary_outlier": {"type": "boolean", "index": 25, "name": "is_primary_outlier", "comment": null}, "binomial_x_delinq_loans": {"type": "numeric", "index": 26, "name": "binomial_x_delinq_loans", "comment": null}, "binomial_n_active_loans": {"type": "numeric", "index": 27, "name": "binomial_n_active_loans", "comment": null}, "delinq_30plus_upb": {"type": "numeric", "index": 28, "name": "delinq_30plus_upb", "comment": null}, "active_upb": {"type": "numeric", "index": 29, "name": "active_upb", "comment": null}, "binomial_p_hat": {"type": "numeric", "index": 30, "name": "binomial_p_hat", "comment": null}, "wilson_95_lo": {"type": "numeric", "index": 31, "name": "wilson_95_lo", "comment": null}, "wilson_95_hi": {"type": "numeric", "index": 32, "name": "wilson_95_hi", "comment": null}, "upb_rate_normal_approx_95_lo": {"type": "numeric", "index": 33, "name": "upb_rate_normal_approx_95_lo", "comment": null}, "upb_rate_normal_approx_95_hi": {"type": "numeric", "index": 34, "name": "upb_rate_normal_approx_95_hi", "comment": null}}, "stats": {"has_stats": {"id": "has_stats", "label": "Has Stats?", "value": false, "include": false, "description": "Indicates whether there are statistics for this table"}}, "unique_id": "model.mortgage_analytics.fct_portfolio_metric_significance_monthly"}, "model.mortgage_analytics.fct_portfolio_metric_significance_monthly_wide": {"metadata": {"type": "VIEW", "schema": "analytics_mart_mortgage", "name": "fct_portfolio_metric_significance_monthly_wide", "database": "neondb", "comment": "Convenience wide view of the significance table for dashboarding.", "owner": "neondb_owner"}, "columns": {"reporting_month": {"type": "date", "index": 1, "name": "reporting_month", "comment": null}, "active_loan_count": {"type": "numeric", "index": 2, "name": "active_loan_count", "comment": null}, "delinq_30plus_loan_count": {"type": "numeric", "index": 3, "name": "delinq_30plus_loan_count", "comment": null}, "delinquency_rate_30_plus": {"type": "numeric", "index": 4, "name": "delinquency_rate_30_plus", "comment": null}, "wilson_95_lo_delinquency_rate_30_plus": {"type": "numeric", "index": 5, "name": "wilson_95_lo_delinquency_rate_30_plus", "comment": null}, "wilson_95_hi_delinquency_rate_30_plus": {"type": "numeric", "index": 6, "name": "wilson_95_hi_delinquency_rate_30_plus", "comment": null}, "binomial_n_active_loans_delinquency_rate": {"type": "numeric", "index": 7, "name": "binomial_n_active_loans_delinquency_rate", "comment": null}, "binomial_x_delinq_loans_delinquency_rate": {"type": "numeric", "index": 8, "name": "binomial_x_delinq_loans_delinquency_rate", "comment": null}, "active_upb": {"type": "numeric", "index": 9, "name": "active_upb", "comment": null}, "delinq_30plus_upb": {"type": "numeric", "index": 10, "name": "delinq_30plus_upb", "comment": null}, "delinquency_upb_rate_30_plus": {"type": "numeric", "index": 11, "name": "delinquency_upb_rate_30_plus", "comment": null}, "upb_rate_normal_approx_95_lo": {"type": "numeric", "index": 12, "name": "upb_rate_normal_approx_95_lo", "comment": null}, "upb_rate_normal_approx_95_hi": {"type": "numeric", "index": 13, "name": "upb_rate_normal_approx_95_hi", "comment": null}, "mom_delta_active_loan_count": {"type": "numeric", "index": 14, "name": "mom_delta_active_loan_count", "comment": null}, "mom_delta_delinq_30plus_loan_count": {"type": "numeric", "index": 15, "name": "mom_delta_delinq_30plus_loan_count", "comment": null}, "mom_delta_delinquency_rate_30_plus": {"type": "numeric", "index": 16, "name": "mom_delta_delinquency_rate_30_plus", "comment": null}, "mom_delta_active_upb": {"type": "numeric", "index": 17, "name": "mom_delta_active_upb", "comment": null}, "mom_delta_delinq_30plus_upb": {"type": "numeric", "index": 18, "name": "mom_delta_delinq_30plus_upb", "comment": null}, "mom_delta_delinquency_upb_rate_30_plus": {"type": "numeric", "index": 19, "name": "mom_delta_delinquency_upb_rate_30_plus", "comment": null}, "mom_pct_change_active_loan_count": {"type": "numeric", "index": 20, "name": "mom_pct_change_active_loan_count", "comment": null}, "mom_pct_change_delinq_30plus_loan_count": {"type": "numeric", "index": 21, "name": "mom_pct_change_delinq_30plus_loan_count", "comment": null}, "mom_pct_change_delinquency_rate_30_plus": {"type": "numeric", "index": 22, "name": "mom_pct_change_delinquency_rate_30_plus", "comment": null}, "mom_pct_change_active_upb": {"type": "numeric", "index": 23, "name": "mom_pct_change_active_upb", "comment": null}, "mom_pct_change_delinq_30plus_upb": {"type": "numeric", "index": 24, "name": "mom_pct_change_delinq_30plus_upb", "comment": null}, "mom_pct_change_delinquency_upb_rate_30_plus": {"type": "numeric", "index": 25, "name": "mom_pct_change_delinquency_upb_rate_30_plus", "comment": null}, "yoy_delta_active_loan_count": {"type": "numeric", "index": 26, "name": "yoy_delta_active_loan_count", "comment": null}, "yoy_delta_delinq_30plus_loan_count": {"type": "numeric", "index": 27, "name": "yoy_delta_delinq_30plus_loan_count", "comment": null}, "yoy_delta_delinquency_rate_30_plus": {"type": "numeric", "index": 28, "name": "yoy_delta_delinquency_rate_30_plus", "comment": null}, "yoy_delta_active_upb": {"type": "numeric", "index": 29, "name": "yoy_delta_active_upb", "comment": null}, "yoy_delta_delinq_30plus_upb": {"type": "numeric", "index": 30, "name": "yoy_delta_delinq_30plus_upb", "comment": null}, "yoy_delta_delinquency_upb_rate_30_plus": {"type": "numeric", "index": 31, "name": "yoy_delta_delinquency_upb_rate_30_plus", "comment": null}, "yoy_pct_change_active_loan_count": {"type": "numeric", "index": 32, "name": "yoy_pct_change_active_loan_count", "comment": null}, "yoy_pct_change_delinq_30plus_loan_count": {"type": "numeric", "index": 33, "name": "yoy_pct_change_delinq_30plus_loan_count", "comment": null}, "yoy_pct_change_delinquency_rate_30_plus": {"type": "numeric", "index": 34, "name": "yoy_pct_change_delinquency_rate_30_plus", "comment": null}, "yoy_pct_change_active_upb": {"type": "numeric", "index": 35, "name": "yoy_pct_change_active_upb", "comment": null}, "yoy_pct_change_delinq_30plus_upb": {"type": "numeric", "index": 36, "name": "yoy_pct_change_delinq_30plus_upb", "comment": null}, "yoy_pct_change_delinquency_upb_rate_30_plus": {"type": "numeric", "index": 37, "name": "yoy_pct_change_delinquency_upb_rate_30_plus", "comment": null}, "zscore_delinquency_rate_30_plus": {"type": "numeric", "index": 38, "name": "zscore_delinquency_rate_30_plus", "comment": null}, "is_2sd_outlier_delinquency_rate_30_plus": {"type": "boolean", "index": 39, "name": "is_2sd_outlier_delinquency_rate_30_plus", "comment": null}, "zscore_delinquency_upb_rate_30_plus": {"type": "numeric", "index": 40, "name": "zscore_delinquency_upb_rate_30_plus", "comment": null}, "is_2sd_outlier_delinquency_upb_rate_30_plus": {"type": "boolean", "index": 41, "name": "is_2sd_outlier_delinquency_upb_rate_30_plus", "comment": null}, "zscore_active_loan_count": {"type": "numeric", "index": 42, "name": "zscore_active_loan_count", "comment": null}, "is_2sd_outlier_active_loan_count": {"type": "boolean", "index": 43, "name": "is_2sd_outlier_active_loan_count", "comment": null}, "zscore_delinq_30plus_loan_count": {"type": "numeric", "index": 44, "name": "zscore_delinq_30plus_loan_count", "comment": null}, "is_2sd_outlier_delinq_30plus_loan_count": {"type": "boolean", "index": 45, "name": "is_2sd_outlier_delinq_30plus_loan_count", "comment": null}, "zscore_active_upb": {"type": "numeric", "index": 46, "name": "zscore_active_upb", "comment": null}, "is_2sd_outlier_active_upb": {"type": "boolean", "index": 47, "name": "is_2sd_outlier_active_upb", "comment": null}, "zscore_delinq_30plus_upb": {"type": "numeric", "index": 48, "name": "zscore_delinq_30plus_upb", "comment": null}, "is_2sd_outlier_delinq_30plus_upb": {"type": "boolean", "index": 49, "name": "is_2sd_outlier_delinq_30plus_upb", "comment": null}, "robust_zscore_active_loan_count": {"type": "double precision", "index": 50, "name": "robust_zscore_active_loan_count", "comment": null}, "robust_zscore_delinq_30plus_loan_count": {"type": "double precision", "index": 51, "name": "robust_zscore_delinq_30plus_loan_count", "comment": null}, "robust_zscore_delinquency_rate_30_plus": {"type": "double precision", "index": 52, "name": "robust_zscore_delinquency_rate_30_plus", "comment": null}, "robust_zscore_active_upb": {"type": "double precision", "index": 53, "name": "robust_zscore_active_upb", "comment": null}, "robust_zscore_delinq_30plus_upb": {"type": "double precision", "index": 54, "name": "robust_zscore_delinq_30plus_upb", "comment": null}, "robust_zscore_delinquency_upb_rate_30_plus": {"type": "double precision", "index": 55, "name": "robust_zscore_delinquency_upb_rate_30_plus", "comment": null}, "percentile_rank_12m_active_loan_count": {"type": "numeric", "index": 56, "name": "percentile_rank_12m_active_loan_count", "comment": null}, "percentile_rank_12m_delinq_30plus_loan_count": {"type": "numeric", "index": 57, "name": "percentile_rank_12m_delinq_30plus_loan_count", "comment": null}, "percentile_rank_12m_delinquency_rate_30_plus": {"type": "numeric", "index": 58, "name": "percentile_rank_12m_delinquency_rate_30_plus", "comment": null}, "percentile_rank_12m_active_upb": {"type": "numeric", "index": 59, "name": "percentile_rank_12m_active_upb", "comment": null}, "percentile_rank_12m_delinq_30plus_upb": {"type": "numeric", "index": 60, "name": "percentile_rank_12m_delinq_30plus_upb", "comment": null}, "percentile_rank_12m_delinquency_upb_rate_30_plus": {"type": "numeric", "index": 61, "name": "percentile_rank_12m_delinquency_upb_rate_30_plus", "comment": null}, "primary_anomaly_score_active_loan_count": {"type": "double precision", "index": 62, "name": "primary_anomaly_score_active_loan_count", "comment": null}, "primary_anomaly_score_delinq_30plus_loan_count": {"type": "double precision", "index": 63, "name": "primary_anomaly_score_delinq_30plus_loan_count", "comment": null}, "primary_anomaly_score_delinquency_rate_30_plus": {"type": "double precision", "index": 64, "name": "primary_anomaly_score_delinquency_rate_30_plus", "comment": null}, "primary_anomaly_score_active_upb": {"type": "double precision", "index": 65, "name": "primary_anomaly_score_active_upb", "comment": null}, "primary_anomaly_score_delinq_30plus_upb": {"type": "double precision", "index": 66, "name": "primary_anomaly_score_delinq_30plus_upb", "comment": null}, "primary_anomaly_score_delinquency_upb_rate_30_plus": {"type": "double precision", "index": 67, "name": "primary_anomaly_score_delinquency_upb_rate_30_plus", "comment": null}, "recommended_method_active_loan_count": {"type": "text", "index": 68, "name": "recommended_method_active_loan_count", "comment": null}, "recommended_method_delinq_30plus_loan_count": {"type": "text", "index": 69, "name": "recommended_method_delinq_30plus_loan_count", "comment": null}, "recommended_method_delinquency_rate_30_plus": {"type": "text", "index": 70, "name": "recommended_method_delinquency_rate_30_plus", "comment": null}, "recommended_method_active_upb": {"type": "text", "index": 71, "name": "recommended_method_active_upb", "comment": null}, "recommended_method_delinq_30plus_upb": {"type": "text", "index": 72, "name": "recommended_method_delinq_30plus_upb", "comment": null}, "recommended_method_delinquency_upb_rate_30_plus": {"type": "text", "index": 73, "name": "recommended_method_delinquency_upb_rate_30_plus", "comment": null}, "distribution_profile_active_loan_count": {"type": "text", "index": 74, "name": "distribution_profile_active_loan_count", "comment": null}, "distribution_profile_delinq_30plus_loan_count": {"type": "text", "index": 75, "name": "distribution_profile_delinq_30plus_loan_count", "comment": null}, "distribution_profile_delinquency_rate_30_plus": {"type": "text", "index": 76, "name": "distribution_profile_delinquency_rate_30_plus", "comment": null}, "distribution_profile_active_upb": {"type": "text", "index": 77, "name": "distribution_profile_active_upb", "comment": null}, "distribution_profile_delinq_30plus_upb": {"type": "text", "index": 78, "name": "distribution_profile_delinq_30plus_upb", "comment": null}, "distribution_profile_delinquency_upb_rate_30_plus": {"type": "text", "index": 79, "name": "distribution_profile_delinquency_upb_rate_30_plus", "comment": null}, "is_primary_outlier_active_loan_count": {"type": "boolean", "index": 80, "name": "is_primary_outlier_active_loan_count", "comment": null}, "is_primary_outlier_delinq_30plus_loan_count": {"type": "boolean", "index": 81, "name": "is_primary_outlier_delinq_30plus_loan_count", "comment": null}, "is_primary_outlier_delinquency_rate_30_plus": {"type": "boolean", "index": 82, "name": "is_primary_outlier_delinquency_rate_30_plus", "comment": null}, "is_primary_outlier_active_upb": {"type": "boolean", "index": 83, "name": "is_primary_outlier_active_upb", "comment": null}, "is_primary_outlier_delinq_30plus_upb": {"type": "boolean", "index": 84, "name": "is_primary_outlier_delinq_30plus_upb", "comment": null}, "is_primary_outlier_delinquency_upb_rate_30_plus": {"type": "boolean", "index": 85, "name": "is_primary_outlier_delinquency_upb_rate_30_plus", "comment": null}}, "stats": {"has_stats": {"id": "has_stats", "label": "Has Stats?", "value": false, "include": false, "description": "Indicates whether there are statistics for this table"}}, "unique_id": "model.mortgage_analytics.fct_portfolio_metric_significance_monthly_wide"}, "model.mortgage_analytics.fct_portfolio_monthly": {"metadata": {"type": "BASE TABLE", "schema": "analytics_mart_mortgage", "name": "fct_portfolio_monthly", "database": "neondb", "comment": "Monthly portfolio metrics by delinquency bucket.", "owner": "neondb_owner"}, "columns": {"reporting_month": {"type": "date", "index": 1, "name": "reporting_month", "comment": null}, "delinquency_bucket": {"type": "text", "index": 2, "name": "delinquency_bucket", "comment": null}, "loan_record_count": {"type": "bigint", "index": 3, "name": "loan_record_count", "comment": null}, "distinct_loan_count": {"type": "bigint", "index": 4, "name": "distinct_loan_count", "comment": null}, "total_current_actual_upb": {"type": "numeric", "index": 5, "name": "total_current_actual_upb", "comment": null}, "avg_current_interest_rate": {"type": "numeric", "index": 6, "name": "avg_current_interest_rate", "comment": null}, "loan_share_of_month": {"type": "numeric", "index": 7, "name": "loan_share_of_month", "comment": null}, "upb_share_of_month": {"type": "numeric", "index": 8, "name": "upb_share_of_month", "comment": null}, "prior_month_distinct_loan_count": {"type": "bigint", "index": 9, "name": "prior_month_distinct_loan_count", "comment": null}, "prior_month_total_current_actual_upb": {"type": "numeric", "index": 10, "name": "prior_month_total_current_actual_upb", "comment": null}, "mom_distinct_loan_count_delta": {"type": "bigint", "index": 11, "name": "mom_distinct_loan_count_delta", "comment": null}, "mom_total_current_actual_upb_delta": {"type": "numeric", "index": 12, "name": "mom_total_current_actual_upb_delta", "comment": null}}, "stats": {"has_stats": {"id": "has_stats", "label": "Has Stats?", "value": false, "include": false, "description": "Indicates whether there are statistics for this table"}}, "unique_id": "model.mortgage_analytics.fct_portfolio_monthly"}, "model.mortgage_analytics.fct_portfolio_monthly_kpis": {"metadata": {"type": "BASE TABLE", "schema": "analytics_mart_mortgage", "name": "fct_portfolio_monthly_kpis", "database": "neondb", "comment": "Portfolio-level KPIs including delinquency rate, MoM deltas, rolling averages, and z-scores.", "owner": "neondb_owner"}, "columns": {"reporting_month": {"type": "date", "index": 1, "name": "reporting_month", "comment": null}, "active_loan_count": {"type": "numeric", "index": 2, "name": "active_loan_count", "comment": null}, "delinq_30plus_loan_count": {"type": "numeric", "index": 3, "name": "delinq_30plus_loan_count", "comment": null}, "delinquency_rate_30_plus": {"type": "numeric", "index": 4, "name": "delinquency_rate_30_plus", "comment": null}, "active_upb": {"type": "numeric", "index": 5, "name": "active_upb", "comment": null}, "delinq_30plus_upb": {"type": "numeric", "index": 6, "name": "delinq_30plus_upb", "comment": null}, "delinquency_upb_rate_30_plus": {"type": "numeric", "index": 7, "name": "delinquency_upb_rate_30_plus", "comment": null}, "prior_delinq_rate_30_plus": {"type": "numeric", "index": 8, "name": "prior_delinq_rate_30_plus", "comment": null}, "mom_delinq_rate_30_plus_delta": {"type": "numeric", "index": 9, "name": "mom_delinq_rate_30_plus_delta", "comment": null}, "prior_delinq_upb_rate_30_plus": {"type": "numeric", "index": 10, "name": "prior_delinq_upb_rate_30_plus", "comment": null}, "mom_delinq_upb_rate_30_plus_delta": {"type": "numeric", "index": 11, "name": "mom_delinq_upb_rate_30_plus_delta", "comment": null}, "rolling_avg_12m_delinq_rate_30_plus": {"type": "numeric", "index": 12, "name": "rolling_avg_12m_delinq_rate_30_plus", "comment": null}, "rolling_stddev_12m_delinq_rate_30_plus": {"type": "numeric", "index": 13, "name": "rolling_stddev_12m_delinq_rate_30_plus", "comment": null}, "zscore_delinq_rate_30_plus": {"type": "numeric", "index": 14, "name": "zscore_delinq_rate_30_plus", "comment": null}}, "stats": {"has_stats": {"id": "has_stats", "label": "Has Stats?", "value": false, "include": false, "description": "Indicates whether there are statistics for this table"}}, "unique_id": "model.mortgage_analytics.fct_portfolio_monthly_kpis"}, "model.mortgage_analytics.fct_vintage_monthly": {"metadata": {"type": "BASE TABLE", "schema": "analytics_mart_mortgage", "name": "fct_vintage_monthly", "database": "neondb", "comment": "Vintage cohort metrics aggregated at cohort+month grain.", "owner": "neondb_owner"}, "columns": {"vintage_year": {"type": "smallint", "index": 1, "name": "vintage_year", "comment": null}, "vintage_quarter": {"type": "smallint", "index": 2, "name": "vintage_quarter", "comment": null}, "vintage_month": {"type": "integer", "index": 3, "name": "vintage_month", "comment": null}, "reporting_month": {"type": "date", "index": 4, "name": "reporting_month", "comment": null}, "distinct_loan_count": {"type": "bigint", "index": 5, "name": "distinct_loan_count", "comment": null}, "total_current_actual_upb": {"type": "numeric", "index": 6, "name": "total_current_actual_upb", "comment": null}, "delinq_30plus_loan_records": {"type": "bigint", "index": 7, "name": "delinq_30plus_loan_records", "comment": null}, "active_loan_records": {"type": "bigint", "index": 8, "name": "active_loan_records", "comment": null}, "delinquency_rate_30_plus": {"type": "numeric", "index": 9, "name": "delinquency_rate_30_plus", "comment": null}, "delinq_30plus_upb": {"type": "numeric", "index": 10, "name": "delinq_30plus_upb", "comment": null}, "active_upb": {"type": "numeric", "index": 11, "name": "active_upb", "comment": null}, "delinquency_upb_rate_30_plus": {"type": "numeric", "index": 12, "name": "delinquency_upb_rate_30_plus", "comment": null}}, "stats": {"has_stats": {"id": "has_stats", "label": "Has Stats?", "value": false, "include": false, "description": "Indicates whether there are statistics for this table"}}, "unique_id": "model.mortgage_analytics.fct_vintage_monthly"}, "model.mortgage_analytics.stg_freddie_monthly_performance": {"metadata": {"type": "VIEW", "schema": "analytics_stg_mortgage", "name": "stg_freddie_monthly_performance", "database": "neondb", "comment": "Cleaned and typed staging view over raw Freddie monthly performance rows.", "owner": "neondb_owner"}, "columns": {"loan_id": {"type": "text", "index": 1, "name": "loan_id", "comment": null}, "reporting_month": {"type": "date", "index": 2, "name": "reporting_month", "comment": null}, "current_actual_upb": {"type": "numeric", "index": 3, "name": "current_actual_upb", "comment": null}, "delinquency_status_code": {"type": "text", "index": 4, "name": "delinquency_status_code", "comment": null}, "loan_age_months": {"type": "integer", "index": 5, "name": "loan_age_months", "comment": null}, "remaining_months_to_legal_maturity": {"type": "integer", "index": 6, "name": "remaining_months_to_legal_maturity", "comment": null}, "repurchase_flag": {"type": "text", "index": 7, "name": "repurchase_flag", "comment": null}, "modification_flag": {"type": "text", "index": 8, "name": "modification_flag", "comment": null}, "zero_balance_code": {"type": "text", "index": 9, "name": "zero_balance_code", "comment": null}, "zero_balance_effective_date": {"type": "date", "index": 10, "name": "zero_balance_effective_date", "comment": null}, "current_interest_rate": {"type": "numeric", "index": 11, "name": "current_interest_rate", "comment": null}, "current_deferred_upb": {"type": "numeric", "index": 12, "name": "current_deferred_upb", "comment": null}, "due_date_last_paid_installment": {"type": "date", "index": 13, "name": "due_date_last_paid_installment", "comment": null}, "mi_recoveries_raw": {"type": "text", "index": 14, "name": "mi_recoveries_raw", "comment": null}, "net_sales_proceeds_raw": {"type": "text", "index": 15, "name": "net_sales_proceeds_raw", "comment": null}, "non_mi_recoveries_raw": {"type": "text", "index": 16, "name": "non_mi_recoveries_raw", "comment": null}, "expenses": {"type": "numeric", "index": 17, "name": "expenses", "comment": null}, "legal_costs": {"type": "numeric", "index": 18, "name": "legal_costs", "comment": null}, "maintenance_preservation_costs": {"type": "numeric", "index": 19, "name": "maintenance_preservation_costs", "comment": null}, "taxes_and_insurance": {"type": "numeric", "index": 20, "name": "taxes_and_insurance", "comment": null}, "miscellaneous_expenses": {"type": "numeric", "index": 21, "name": "miscellaneous_expenses", "comment": null}, "actual_loss_calculation": {"type": "numeric", "index": 22, "name": "actual_loss_calculation", "comment": null}, "modification_cost": {"type": "numeric", "index": 23, "name": "modification_cost", "comment": null}, "step_modification_flag": {"type": "text", "index": 24, "name": "step_modification_flag", "comment": null}, "deferred_payment_plan": {"type": "text", "index": 25, "name": "deferred_payment_plan", "comment": null}, "estimated_loan_to_value": {"type": "numeric", "index": 26, "name": "estimated_loan_to_value", "comment": null}, "zero_balance_removal_upb": {"type": "numeric", "index": 27, "name": "zero_balance_removal_upb", "comment": null}, "delinquent_accrued_interest": {"type": "numeric", "index": 28, "name": "delinquent_accrued_interest", "comment": null}, "delinquency_due_to_disaster": {"type": "text", "index": 29, "name": "delinquency_due_to_disaster", "comment": null}, "borrower_assistance_plan": {"type": "text", "index": 30, "name": "borrower_assistance_plan", "comment": null}, "current_month_modification_cost": {"type": "numeric", "index": 31, "name": "current_month_modification_cost", "comment": null}, "interest_bearing_upb": {"type": "numeric", "index": 32, "name": "interest_bearing_upb", "comment": null}, "source_year": {"type": "smallint", "index": 33, "name": "source_year", "comment": null}, "source_quarter": {"type": "smallint", "index": 34, "name": "source_quarter", "comment": null}, "source_file_name": {"type": "text", "index": 35, "name": "source_file_name", "comment": null}, "source_folder": {"type": "text", "index": 36, "name": "source_folder", "comment": null}, "ingested_at": {"type": "timestamp with time zone", "index": 37, "name": "ingested_at", "comment": null}}, "stats": {"has_stats": {"id": "has_stats", "label": "Has Stats?", "value": false, "include": false, "description": "Indicates whether there are statistics for this table"}}, "unique_id": "model.mortgage_analytics.stg_freddie_monthly_performance"}, "model.mortgage_analytics.stg_freddie_origination": {"metadata": {"type": "VIEW", "schema": "analytics_stg_mortgage", "name": "stg_freddie_origination", "database": "neondb", "comment": "Cleaned and typed staging view over raw Freddie origination rows.", "owner": "neondb_owner"}, "columns": {"loan_id": {"type": "text", "index": 1, "name": "loan_id", "comment": "Freddie loan sequence number."}, "credit_score": {"type": "integer", "index": 2, "name": "credit_score", "comment": null}, "first_payment_date": {"type": "date", "index": 3, "name": "first_payment_date", "comment": null}, "first_time_homebuyer_flag": {"type": "text", "index": 4, "name": "first_time_homebuyer_flag", "comment": null}, "maturity_date": {"type": "date", "index": 5, "name": "maturity_date", "comment": null}, "msa_md_code": {"type": "text", "index": 6, "name": "msa_md_code", "comment": null}, "mortgage_insurance_pct": {"type": "numeric", "index": 7, "name": "mortgage_insurance_pct", "comment": null}, "number_of_units": {"type": "integer", "index": 8, "name": "number_of_units", "comment": null}, "occupancy_status": {"type": "text", "index": 9, "name": "occupancy_status", "comment": null}, "original_cltv": {"type": "numeric", "index": 10, "name": "original_cltv", "comment": null}, "original_dti": {"type": "numeric", "index": 11, "name": "original_dti", "comment": null}, "original_upb": {"type": "bigint", "index": 12, "name": "original_upb", "comment": null}, "original_ltv": {"type": "numeric", "index": 13, "name": "original_ltv", "comment": null}, "original_interest_rate": {"type": "numeric", "index": 14, "name": "original_interest_rate", "comment": null}, "channel": {"type": "text", "index": 15, "name": "channel", "comment": null}, "ppm_flag": {"type": "text", "index": 16, "name": "ppm_flag", "comment": null}, "product_type": {"type": "text", "index": 17, "name": "product_type", "comment": null}, "property_state": {"type": "text", "index": 18, "name": "property_state", "comment": null}, "property_type": {"type": "text", "index": 19, "name": "property_type", "comment": null}, "postal_code": {"type": "text", "index": 20, "name": "postal_code", "comment": null}, "loan_purpose": {"type": "text", "index": 21, "name": "loan_purpose", "comment": null}, "original_loan_term_months": {"type": "integer", "index": 22, "name": "original_loan_term_months", "comment": null}, "number_of_borrowers": {"type": "integer", "index": 23, "name": "number_of_borrowers", "comment": null}, "seller_name": {"type": "text", "index": 24, "name": "seller_name", "comment": null}, "servicer_name": {"type": "text", "index": 25, "name": "servicer_name", "comment": null}, "super_conforming_flag": {"type": "text", "index": 26, "name": "super_conforming_flag", "comment": null}, "preharp_loan_identifier": {"type": "text", "index": 27, "name": "preharp_loan_identifier", "comment": null}, "harp_loan_indicator": {"type": "text", "index": 28, "name": "harp_loan_indicator", "comment": null}, "program_indicator": {"type": "text", "index": 29, "name": "program_indicator", "comment": null}, "property_valuation_method": {"type": "text", "index": 30, "name": "property_valuation_method", "comment": null}, "interest_only_indicator": {"type": "text", "index": 31, "name": "interest_only_indicator", "comment": null}, "mortgage_insurance_cancellation_indicator": {"type": "text", "index": 32, "name": "mortgage_insurance_cancellation_indicator", "comment": null}, "source_year": {"type": "smallint", "index": 33, "name": "source_year", "comment": null}, "source_quarter": {"type": "smallint", "index": 34, "name": "source_quarter", "comment": null}, "source_file_name": {"type": "text", "index": 35, "name": "source_file_name", "comment": null}, "source_folder": {"type": "text", "index": 36, "name": "source_folder", "comment": null}, "ingested_at": {"type": "timestamp with time zone", "index": 37, "name": "ingested_at", "comment": null}}, "stats": {"has_stats": {"id": "has_stats", "label": "Has Stats?", "value": false, "include": false, "description": "Indicates whether there are statistics for this table"}}, "unique_id": "model.mortgage_analytics.stg_freddie_origination"}}, "sources": {"source.mortgage_analytics.raw_freddie.monthly_performance_raw": {"metadata": {"type": "BASE TABLE", "schema": "raw_freddie", "name": "monthly_performance_raw", "database": "neondb", "comment": null, "owner": "neondb_owner"}, "columns": {"loan_sequence_number": {"type": "text", "index": 1, "name": "loan_sequence_number", "comment": null}, "monthly_reporting_period": {"type": "text", "index": 2, "name": "monthly_reporting_period", "comment": null}, "current_actual_upb": {"type": "text", "index": 3, "name": "current_actual_upb", "comment": null}, "current_loan_delinquency_status": {"type": "text", "index": 4, "name": "current_loan_delinquency_status", "comment": null}, "loan_age": {"type": "text", "index": 5, "name": "loan_age", "comment": null}, "remaining_months_to_legal_maturity": {"type": "text", "index": 6, "name": "remaining_months_to_legal_maturity", "comment": null}, "repurchase_flag": {"type": "text", "index": 7, "name": "repurchase_flag", "comment": null}, "modification_flag": {"type": "text", "index": 8, "name": "modification_flag", "comment": null}, "zero_balance_code": {"type": "text", "index": 9, "name": "zero_balance_code", "comment": null}, "zero_balance_effective_date": {"type": "text", "index": 10, "name": "zero_balance_effective_date", "comment": null}, "current_interest_rate": {"type": "text", "index": 11, "name": "current_interest_rate", "comment": null}, "current_deferred_upb": {"type": "text", "index": 12, "name": "current_deferred_upb", "comment": null}, "due_date_last_paid_installment": {"type": "text", "index": 13, "name": "due_date_last_paid_installment", "comment": null}, "mi_recoveries": {"type": "text", "index": 14, "name": "mi_recoveries", "comment": null}, "net_sales_proceeds": {"type": "text", "index": 15, "name": "net_sales_proceeds", "comment": null}, "non_mi_recoveries": {"type": "text", "index": 16, "name": "non_mi_recoveries", "comment": null}, "expenses": {"type": "text", "index": 17, "name": "expenses", "comment": null}, "legal_costs": {"type": "text", "index": 18, "name": "legal_costs", "comment": null}, "maintenance_preservation_costs": {"type": "text", "index": 19, "name": "maintenance_preservation_costs", "comment": null}, "taxes_and_insurance": {"type": "text", "index": 20, "name": "taxes_and_insurance", "comment": null}, "miscellaneous_expenses": {"type": "text", "index": 21, "name": "miscellaneous_expenses", "comment": null}, "actual_loss_calculation": {"type": "text", "index": 22, "name": "actual_loss_calculation", "comment": null}, "modification_cost": {"type": "text", "index": 23, "name": "modification_cost", "comment": null}, "step_modification_flag": {"type": "text", "index": 24, "name": "step_modification_flag", "comment": null}, "deferred_payment_plan": {"type": "text", "index": 25, "name": "deferred_payment_plan", "comment": null}, "estimated_loan_to_value": {"type": "text", "index": 26, "name": "estimated_loan_to_value", "comment": null}, "zero_balance_removal_upb": {"type": "text", "index": 27, "name": "zero_balance_removal_upb", "comment": null}, "delinquent_accrued_interest": {"type": "text", "index": 28, "name": "delinquent_accrued_interest", "comment": null}, "delinquency_due_to_disaster": {"type": "text", "index": 29, "name": "delinquency_due_to_disaster", "comment": null}, "borrower_assistance_plan": {"type": "text", "index": 30, "name": "borrower_assistance_plan", "comment": null}, "current_month_modification_cost": {"type": "text", "index": 31, "name": "current_month_modification_cost", "comment": null}, "interest_bearing_upb": {"type": "text", "index": 32, "name": "interest_bearing_upb", "comment": null}, "source_year": {"type": "smallint", "index": 33, "name": "source_year", "comment": null}, "source_quarter": {"type": "smallint", "index": 34, "name": "source_quarter", "comment": null}, "source_file_name": {"type": "text", "index": 35, "name": "source_file_name", "comment": null}, "source_folder": {"type": "text", "index": 36, "name": "source_folder", "comment": null}, "ingested_at": {"type": "timestamp with time zone", "index": 37, "name": "ingested_at", "comment": null}}, "stats": {"has_stats": {"id": "has_stats", "label": "Has Stats?", "value": false, "include": false, "description": "Indicates whether there are statistics for this table"}}, "unique_id": "source.mortgage_analytics.raw_freddie.monthly_performance_raw"}, "source.mortgage_analytics.raw_freddie.origination_raw": {"metadata": {"type": "BASE TABLE", "schema": "raw_freddie", "name": "origination_raw", "database": "neondb", "comment": null, "owner": "neondb_owner"}, "columns": {"credit_score": {"type": "text", "index": 1, "name": "credit_score", "comment": null}, "first_payment_date": {"type": "text", "index": 2, "name": "first_payment_date", "comment": null}, "first_time_homebuyer_flag": {"type": "text", "index": 3, "name": "first_time_homebuyer_flag", "comment": null}, "maturity_date": {"type": "text", "index": 4, "name": "maturity_date", "comment": null}, "msa_md_code": {"type": "text", "index": 5, "name": "msa_md_code", "comment": null}, "mortgage_insurance_percentage": {"type": "text", "index": 6, "name": "mortgage_insurance_percentage", "comment": null}, "number_of_units": {"type": "text", "index": 7, "name": "number_of_units", "comment": null}, "occupancy_status": {"type": "text", "index": 8, "name": "occupancy_status", "comment": null}, "original_cltv": {"type": "text", "index": 9, "name": "original_cltv", "comment": null}, "original_dti": {"type": "text", "index": 10, "name": "original_dti", "comment": null}, "original_upb": {"type": "text", "index": 11, "name": "original_upb", "comment": null}, "original_ltv": {"type": "text", "index": 12, "name": "original_ltv", "comment": null}, "original_interest_rate": {"type": "text", "index": 13, "name": "original_interest_rate", "comment": null}, "channel": {"type": "text", "index": 14, "name": "channel", "comment": null}, "ppm_flag": {"type": "text", "index": 15, "name": "ppm_flag", "comment": null}, "product_type": {"type": "text", "index": 16, "name": "product_type", "comment": null}, "property_state": {"type": "text", "index": 17, "name": "property_state", "comment": null}, "property_type": {"type": "text", "index": 18, "name": "property_type", "comment": null}, "postal_code": {"type": "text", "index": 19, "name": "postal_code", "comment": null}, "loan_sequence_number": {"type": "text", "index": 20, "name": "loan_sequence_number", "comment": null}, "loan_purpose": {"type": "text", "index": 21, "name": "loan_purpose", "comment": null}, "original_loan_term": {"type": "text", "index": 22, "name": "original_loan_term", "comment": null}, "number_of_borrowers": {"type": "text", "index": 23, "name": "number_of_borrowers", "comment": null}, "seller_name": {"type": "text", "index": 24, "name": "seller_name", "comment": null}, "servicer_name": {"type": "text", "index": 25, "name": "servicer_name", "comment": null}, "super_conforming_flag": {"type": "text", "index": 26, "name": "super_conforming_flag", "comment": null}, "preharp_loan_identifier": {"type": "text", "index": 27, "name": "preharp_loan_identifier", "comment": null}, "harp_loan_indicator": {"type": "text", "index": 28, "name": "harp_loan_indicator", "comment": null}, "program_indicator": {"type": "text", "index": 29, "name": "program_indicator", "comment": null}, "property_valuation_method": {"type": "text", "index": 30, "name": "property_valuation_method", "comment": null}, "interest_only_indicator": {"type": "text", "index": 31, "name": "interest_only_indicator", "comment": null}, "mortgage_insurance_cancellation_indicator": {"type": "text", "index": 32, "name": "mortgage_insurance_cancellation_indicator", "comment": null}, "source_year": {"type": "smallint", "index": 33, "name": "source_year", "comment": null}, "source_quarter": {"type": "smallint", "index": 34, "name": "source_quarter", "comment": null}, "source_file_name": {"type": "text", "index": 35, "name": "source_file_name", "comment": null}, "source_folder": {"type": "text", "index": 36, "name": "source_folder", "comment": null}, "ingested_at": {"type": "timestamp with time zone", "index": 37, "name": "ingested_at", "comment": null}}, "stats": {"has_stats": {"id": "has_stats", "label": "Has Stats?", "value": false, "include": false, "description": "Indicates whether there are statistics for this table"}}, "unique_id": "source.mortgage_analytics.raw_freddie.origination_raw"}}, "errors": null}